odoo/addons/product_multi_company_stock/README.rst
odoo/addons/product_multi_company_stock/__init__.py
odoo/addons/product_multi_company_stock/__manifest__.py
odoo/addons/product_multi_company_stock/i18n/it.po
odoo/addons/product_multi_company_stock/i18n/product_multi_company_stock.pot
odoo/addons/product_multi_company_stock/models/__init__.py
odoo/addons/product_multi_company_stock/models/product_template.py
odoo/addons/product_multi_company_stock/readme/CONTRIBUTORS.md
odoo/addons/product_multi_company_stock/readme/DESCRIPTION.md
odoo/addons/product_multi_company_stock/static/description/icon.png
odoo/addons/product_multi_company_stock/static/description/index.html
odoo/addons/product_multi_company_stock/tests/__init__.py
odoo/addons/product_multi_company_stock/tests/test_product_multi_company_stock.py
odoo_addon_product_multi_company_stock-18.0.1.0.0.6.dist-info/METADATA
odoo_addon_product_multi_company_stock-18.0.1.0.0.6.dist-info/WHEEL
odoo_addon_product_multi_company_stock-18.0.1.0.0.6.dist-info/top_level.txt
odoo_addon_product_multi_company_stock-18.0.1.0.0.6.dist-info/RECORD
