Metadata-Version: 2.1
Name: odoo-addon-product_multi_company_stock
Version: 18.0.1.0.0.6
Requires-Python: >=3.10
Requires-Dist: odoo-addon-product_multi_company==18.0.*
Requires-Dist: odoo==18.0.*
Summary: Does not allow to remove company if there is stock or moves in that company
Home-page: https://github.com/OCA/multi-company
License: AGPL-3
Author: ForgeFlow,Odoo Community Association (OCA)
Author-email: support@odoo-community.org
Classifier: Programming Language :: Python
Classifier: Framework :: Odoo
Classifier: Framework :: Odoo :: 18.0
Classifier: License :: OSI Approved :: GNU Affero General Public License v3
